safemd/__init__.py
safemd/clean.py
safemd/renderer.py
tests/payloads/__init__.py
tests/payloads/expected_output.py
tests/payloads/md_input.py
safemd-19.10.1.dist-info/LICENSE
safemd-19.10.1.dist-info/METADATA
safemd-19.10.1.dist-info/WHEEL
safemd-19.10.1.dist-info/top_level.txt
safemd-19.10.1.dist-info/RECORD
