Metadata-Version: 2.1
Name: safemd
Version: 19.10.1
Summary: A markdown renderer focusing on security first
Home-page: https://github.com/Hultner/safemd/
Author: Alexander Hultnér
Author-email: ahultner@gmail.com
Maintainer: Alexander Hultnér
Maintainer-email: ahultner@gmail.com
License: UNKNOWN
Platform: UNKNOWN
Classifier: Development Status :: 5 - Production/Stable
Classifier: Environment :: Web Environment
Classifier: Intended Audience :: Developers
Classifier: License :: OSI Approved :: BSD License
Classifier: Operating System :: OS Independent
Classifier: Programming Language :: Python
Classifier: Programming Language :: Python :: 3.6
Classifier: Programming Language :: Python :: 3.7
Classifier: Topic :: Software Development :: Libraries :: Python Modules
Requires-Python: >=3.6
Requires-Dist: cmarkgfm
Requires-Dist: bleach
Provides-Extra: dev
Requires-Dist: black ; extra == 'dev'
Requires-Dist: pytest ; extra == 'dev'
Requires-Dist: twine ; extra == 'dev'
Requires-Dist: pytest-cov ; extra == 'dev'
Requires-Dist: codacy-coverage ; extra == 'dev'
